{
  "type": "minecraft:chest",
  "pools": [
    {
      "rolls": {
        "type": "minecraft:uniform",
        "min": 7.0,
        "max": 15.0
      },
      "bonus_rolls": 1.0,
      "entries": [
        {
          "type": "minecraft:item",
          "weight": 4,
          "functions": [
            {
              "function": "minecraft:set_count",
              "count": {
                "type": "minecraft:uniform",
                "min": 1.0,
                "max": 3.0
              },
              "add": false
            }
          ],
          "name": "minecraft:gold_ingot"
        },
        {
          "type": "minecraft:item",
          "weight": 40,
          "functions": [
            {
              "function": "minecraft:set_count",
              "count": {
                "type": "minecraft:uniform",
                "min": 2.0,
                "max": 6.0
              },
              "add": false
            }
          ],
          "name": "minecraft:gold_nugget"
        },
        {
          "type": "minecraft:item",
          "weight": 1,
          "name": "minecraft:ghast_tear"
        },
        {
          "type": "minecraft:item",
          "weight": 4,
          "name": "minecraft:sugar"
        },
        {
          "type": "minecraft:item",
          "weight": 4,
          "name": "minecraft:melon_slice"
        },
        {
          "type": "minecraft:item",
          "weight": 4,
          "name": "minecraft:magma_cream"
        },
        {
          "type": "minecraft:item",
          "weight": 4,
          "name": "minecraft:blaze_powder"
        },
        {
          "type": "minecraft:item",
          "weight": 4,
          "name": "minecraft:glowstone_dust"
        },
        {
          "type": "minecraft:item",
          "weight": 4,
          "name": "minecraft:phantom_membrane"
        },
        {
          "type": "minecraft:item",
          "weight": 2,
          "name": "minecraft:lava_bucket"
        },
        {
          "type": "minecraft:item",
          "weight": 2,
          "name": "minecraft:lava_bucket"
        },
        {
          "type": "minecraft:item",
          "weight": 2,
          "name": "minecraft:rabbit_foot"
        }
      ]
    }
  ]
}